{"nodes": [{"id": "research_configs_rf_config", "label": "RF Config YAML (test_size=0.20, seed=42)", "file_type": "document", "source_file": "research/configs/rf_config.yaml", "source_location": null, "source_url": null, "captured_at": null, "author": null, "contributor": null}], "edges": [{"source": "research_configs_rf_config", "target": "research_readme_train_rf", "relation": "references", "confidence": "EXTRACTED", "confidence_score": 1.0, "source_file": "research/configs/rf_config.yaml", "source_location": "Usage comment", "weight": 1.0}], "hyperedges": []}